quest_maker_api_shared_library/__init__.py
quest_maker_api_shared_library/custom_types.py
quest_maker_api_shared_library/token_manager.py
quest_maker_api_shared_library/errors/__init__.py
quest_maker_api_shared_library/errors/authentication.py
quest_maker_api_shared_library/errors/authorization.py
quest_maker_api_shared_library/errors/database.py
quest_maker_api_shared_library-1.0.5.dist-info/LICENSE
quest_maker_api_shared_library-1.0.5.dist-info/METADATA
quest_maker_api_shared_library-1.0.5.dist-info/WHEEL
quest_maker_api_shared_library-1.0.5.dist-info/top_level.txt
quest_maker_api_shared_library-1.0.5.dist-info/RECORD
